opentelemetry/semconv/llm/__init__.py
opentelemetry_semantic_conventions_llm-0.0.2.dist-info/METADATA
opentelemetry_semantic_conventions_llm-0.0.2.dist-info/WHEEL
opentelemetry_semantic_conventions_llm-0.0.2.dist-info/RECORD
